{
  "FILE NAME": "11_X001_C185_0929_1.jpg",
  "COLLECTION METHOD": "제작자료",
  "FORM": "이미지",
  "DATE": "2020-09-28 12:07:09",
  "GPS": "37.5001800722222/126.746419827778",
  "ID CODE": "C185",
  "RESOLUTION": "2341*1080",
  "focus distance": "3.93mm",
  "exposure time": "166/10000sec",
  "Aperture values": "1.53",
  "Sensitivity iso": "125",
  "exposure method": "",
  "MAKE": "samsung",
  "Camera Model Name": "SM-A505N",
  "Software": "",
  "File Size": "437925",
  "DAY/NIGHT": "주간",
  "PLACE": "실외",
  "PROJECT SORTING": "생활폐기물",
  "BoundingCount": "1",
  "Bounding": [
    {
      "CLASS": "가구류",
      "DETAILS": "밥상",
      "DAMAGE": "원형",
      "TRANSPARENCY": "불투명",
      "Color": "140/131/124",
      "Shape": "다면체",
      "Texture": "딱딱함",
      "Object Size": "중",
      "Direction": "윗면",
      "Drawing": "BOX",
      "x1": "490",
      "y1": "52",
      "x2": "1982",
      "y2": "1071"
    }
  ]
}