{
  "FILE NAME": "11_X001_C172_0309_0.jpg",
  "COLLECTION METHOD": "제작자료",
  "FORM": "이미지",
  "DATE": "2021-03-09 13:09:45",
  "GPS": "37.5108295277778/126.7275912",
  "ID CODE": "C172",
  "RESOLUTION": "1921*1080",
  "focus distance": "4.30mm",
  "exposure time": "1/216sec",
  "Aperture values": "2.52",
  "Sensitivity iso": "50",
  "exposure method": "normal program",
  "MAKE": "samsung",
  "Camera Model Name": "SM-N960N",
  "Software": "N960NKSU3FTK1",
  "File Size": "438908",
  "DAY/NIGHT": "주간",
  "PLACE": "실외",
  "PROJECT SORTING": "생활폐기물",
  "BoundingCount": "1",
  "Bounding": [
    {
      "CLASS": "가구류",
      "DETAILS": "밥상",
      "DAMAGE": "원형",
      "TRANSPARENCY": "불투명",
      "Color": "174/152/125",
      "Shape": "다면체",
      "Texture": "딱딱함",
      "Object Size": "중",
      "Direction": "원거리",
      "Drawing": "BOX",
      "x1": "707",
      "y1": "249",
      "x2": "1053",
      "y2": "541"
    }
  ]
}